vidarr/__init__.py
vidarr/dali.py
vidarr/distill.py
vidarr/trace_analysis.py
vidarr/trainer.py
vidarr/utils.py
vidarr-0.1.3.dist-info/licenses/LICENSE
vidarr-0.1.3.dist-info/METADATA
vidarr-0.1.3.dist-info/WHEEL
vidarr-0.1.3.dist-info/top_level.txt
vidarr-0.1.3.dist-info/RECORD
