Metadata-Version: 2.4
Name: vidarr
Version: 0.1.3
Summary: Add your description here
Requires-Python: >=3.10
License-File: LICENSE
Requires-Dist: holistictraceanalysis>=0.5.0
Requires-Dist: lightly-train[timm]>=0.11.4
Requires-Dist: nvidia-dali-cuda120>=1.51.2
Requires-Dist: timm>=1.0.21
Requires-Dist: torchmetrics>=1.8.2
Requires-Dist: wandb>=0.23.0
Dynamic: license-file
